malbench/__init__.py
malbench/__main__.py
malbench/args.py
malbench/celebrations.py
malbench/data/banner.txt
malbench/data/disclaimer.txt
malbench/data/version.txt
malbench/malware.py
malbench/message.py
malbench/platform.py
malbench/version.py
malbench-0.4.1.dist-info/entry_points.txt
malbench-0.4.1.dist-info/LICENSE
malbench-0.4.1.dist-info/METADATA
malbench-0.4.1.dist-info/WHEEL
malbench-0.4.1.dist-info/RECORD
