Metadata-Version: 2.1
Name: malbench
Version: 0.4.1
Summary: A tool used to benchmark antivirus solutions against real-world malware samples.
Home-page: https://github.com/youkergav/Malbench
License: GPL-3.0-only
Author: Gavin Youker
Author-email: youkergav@gmail.com
Requires-Python: >=3.8.1,<4.0.0
Classifier: License :: OSI Approved :: GNU General Public License v3 (GPLv3)
Classifier: Programming Language :: Python :: 3
Classifier: Programming Language :: Python :: 3.9
Classifier: Programming Language :: Python :: 3.10
Classifier: Programming Language :: Python :: 3.11
Requires-Dist: colorama (>=0.4.6,<0.5.0)
Requires-Dist: python-dotenv (>=1.0.0,<2.0.0)
Requires-Dist: toml (>=0.10.2,<0.11.0)
Project-URL: Repository, https://github.com/youkergav/Malbench
